textutility/__init__.py
textutility/textutility.py
textutility-0.2.2.dist-info/METADATA
textutility-0.2.2.dist-info/WHEEL
textutility-0.2.2.dist-info/top_level.txt
textutility-0.2.2.dist-info/RECORD
