Metadata-Version: 2.4
Name: textutility
Version: 0.2.2
Summary: Useful string and text manipulation tools
Author: Carlos
Author-email: karlos.santana13@gmail.com
License: MIT
Classifier: Programming Language :: Python :: 3
Classifier: Operating System :: OS Independent
Requires-Python: >=3.7
Dynamic: author
Dynamic: author-email
Dynamic: classifier
Dynamic: description
Dynamic: description-content-type
Dynamic: license
Dynamic: requires-python
Dynamic: summary
